sample_project_ivi/__init__.py
sample_project_ivi/src.py
sample_project_ivi/version.txt
sample_project_ivi-0.0.3.dist-info/LICENSE
sample_project_ivi-0.0.3.dist-info/METADATA
sample_project_ivi-0.0.3.dist-info/WHEEL
sample_project_ivi-0.0.3.dist-info/top_level.txt
sample_project_ivi-0.0.3.dist-info/RECORD
